get_lfs_advisor_cli/__init__.py
get_lfs_advisor_cli/cli.py
git_lfs_advisor_cli-0.1.0.dist-info/METADATA
git_lfs_advisor_cli-0.1.0.dist-info/WHEEL
git_lfs_advisor_cli-0.1.0.dist-info/entry_points.txt
git_lfs_advisor_cli-0.1.0.dist-info/top_level.txt
git_lfs_advisor_cli-0.1.0.dist-info/RECORD
