Metadata-Version: 2.4
Name: git-lfs-advisor-cli
Version: 0.1.0
Summary: A script to find large/binary files and generate Git LFS commands.
Home-page: https://github.com/taicaile/git-lfs-advisor
Author: taicaile
Author-email: 
Project-URL: Bug Tracker, https://github.com/taicaile/git-lfs-advisor/issues
Project-URL: Source Code, https://github.com/taicaile/git-lfs-advisor
Classifier: Programming Language :: Python :: 3
Classifier: License :: OSI Approved :: MIT License
Classifier: Operating System :: OS Independent
Classifier: Environment :: Console
Classifier: Topic :: Software Development :: Version Control :: Git
Requires-Python: >=3.6
Dynamic: author
Dynamic: classifier
Dynamic: description
Dynamic: description-content-type
Dynamic: home-page
Dynamic: project-url
Dynamic: requires-python
Dynamic: summary
